tests/__init__.py
tests/test_game.py
text_adventure_game/__init__.py
text_adventure_game/battle/__init__.py
text_adventure_game/battle/battle.py
text_adventure_game/characters/__init__.py
text_adventure_game/characters/character.py
text_adventure_game/characters/skill.py
text_adventure_game/characters/status.py
text_adventure_game/core/__init__.py
text_adventure_game/core/code.py
text_adventure_game/core/constants.py
text_adventure_game/core/game.py
text_adventure_game/gameplay/__init__.py
text_adventure_game/gameplay/explore.py
text_adventure_game/gameplay/quest.py
text_adventure_game/gameplay/relationship.py
text_adventure_game/gameplay/relationship_manager.py
text_adventure_game/inventory/__init__.py
text_adventure_game/inventory/equipment.py
text_adventure_game/inventory/equipment_view.py
text_adventure_game/inventory/inventory.py
text_adventure_game/inventory/item.py
text_adventure_game/inventory/items.py
text_adventure_game/save/__init__.py
text_adventure_game/save/save_load.py
text_adventure_game-0.1.3.dist-info/LICENSE
text_adventure_game-0.1.3.dist-info/METADATA
text_adventure_game-0.1.3.dist-info/WHEEL
text_adventure_game-0.1.3.dist-info/top_level.txt
text_adventure_game-0.1.3.dist-info/RECORD
