Metadata-Version: 2.1
Name: text-adventure-game
Version: 0.1.3
Summary: 冒险战斗恋爱文字游戏
Home-page: https://github.com/yourusername/text_adventure_game
Author: 将和
Author-email: 1727949032@qq.com
Classifier: Programming Language :: Python :: 3
Classifier: License :: OSI Approved :: MIT License
Classifier: Operating System :: OS Independent
Requires-Python: >=3.6
License-File: LICENSE
Requires-Dist: requests >=2.20.0
